qusi/__init__.py
qusi/finite_standard_light_curve_dataset.py
qusi/finite_standard_light_curve_observation_dataset.py
qusi/finite_test_session.py
qusi/hadryss_model.py
qusi/infer_session.py
qusi/light_curve.py
qusi/light_curve_collection.py
qusi/light_curve_dataset.py
qusi/light_curve_observation.py
qusi/light_curve_transforms.py
qusi/single_dense_layer_model.py
qusi/toy_light_curve_collection.py
qusi/train_hyperparameter_configuration.py
qusi/train_logging_configuration.py
qusi/train_session.py
qusi/train_system_configuration.py
qusi/wandb_liaison.py
ramjet/__init__.py
ramjet/analysis/__init__.py
ramjet/analysis/color_palette.py
ramjet/analysis/convert_column_name_to_display_name.py
ramjet/analysis/light_curve_folding_vizualizer/__init__.py
ramjet/analysis/light_curve_folding_vizualizer/application.py
ramjet/analysis/light_curve_folding_vizualizer/main.py
ramjet/analysis/light_curve_folding_vizualizer/viewer.py
ramjet/analysis/light_curve_visualizer.py
ramjet/analysis/model_loader.py
ramjet/analysis/roc_calculator.py
ramjet/analysis/tess_ffi_variability_viewer/__init__.py
ramjet/analysis/tess_ffi_variability_viewer/main.py
ramjet/analysis/transit_vetter.py
ramjet/analysis/viewer/__init__.py
ramjet/analysis/viewer/light_curve_display.py
ramjet/analysis/viewer/preloader.py
ramjet/analysis/viewer/view_entity.py
ramjet/analysis/viewer/viewer.py
ramjet/data_interface/__init__.py
ramjet/data_interface/metadatabase.py
ramjet/data_interface/moa_data_interface.py
ramjet/data_interface/tess_data_interface.py
ramjet/data_interface/tess_eclipsing_binary_metadata_manager.py
ramjet/data_interface/tess_ffi_light_curve_metadata_manager.py
ramjet/data_interface/tess_target_metadata_manager.py
ramjet/data_interface/tess_toi_data_interface.py
ramjet/data_interface/tess_transit_metadata_manager.py
ramjet/data_interface/tess_two_minute_cadence_light_curve_metadata_manager.py
ramjet/database/__init__.py
ramjet/database/base_model.py
ramjet/database/tess_planet_disposition.py
astroramjet-0.7.2.dist-info/LICENSE
astroramjet-0.7.2.dist-info/METADATA
astroramjet-0.7.2.dist-info/WHEEL
astroramjet-0.7.2.dist-info/entry_points.txt
astroramjet-0.7.2.dist-info/RECORD
